mammograms/__init__.py
mammograms/cases/sfm-benign-0/1-130.dcm
mammograms/cases/sfm-benign-0/1-131.dcm
mammograms/cases/sfm-benign-0/1-132.dcm
mammograms/cases/sfm-benign-0/1-133.dcm
mammograms/cases/sfm-malign-0/1-280.dcm
mammograms/cases/sfm-malign-0/1-281.dcm
mammograms/cases/sfm-malign-0/1-282.dcm
mammograms/cases/sfm-malign-0/1-283.dcm
mammograms/mammograms.py
mammograms/version.py
mammograms-0.0.1.dist-info/WHEEL
mammograms-0.0.1.dist-info/METADATA
mammograms-0.0.1.dist-info/RECORD
