Metadata-Version: 2.1
Name: mammograms
Version: 0.0.1
License: MIT
Author: MedCognetics, Inc.
Requires-Python: >=3.10
